LICENSE
MANIFEST.in
README.md
requirements.txt
setup.py
movienamer/__init__.py
movienamer/confirm.py
movienamer/identify.py
movienamer/keywords.py
movienamer/main.py
movienamer/sanitize.py
movienamer/tmdb.py
movienamer.egg-info/PKG-INFO
movienamer.egg-info/SOURCES.txt
movienamer.egg-info/dependency_links.txt
movienamer.egg-info/entry_points.txt
movienamer.egg-info/requires.txt
movienamer.egg-info/top_level.txt