Metadata-Version: 1.0
Name: movienamer
Version: 0.1.1
Summary: Command-line utility to organize movies
Home-page: https://github.com/divijbindlish/movienamer
Author: Divij Bindlish
Author-email: dvjbndlsh93@gmail.com
License: MIT
Platform: UNKNOWN
